{
  "id": "korean",
  "region": "Eastern Asia",
  "classification": ["traditional"],
  "fallback_to_international_names": false,
  "constellations": [
    {
      "id": "CON korean 001",
      "lines": [[65721, 64792, 64852]],
      "common_name": {"english": "Holy Kettle", "native": "JuJeong"}
    },
    {
      "id": "CON korean 002",
      "lines": [[68520, 66200]],
      "common_name": {"english": "Farm of Capital City", "native": "CheonJeon"}
    },
    {
      "id": "CON korean 003",
      "lines": [[66249, 65474], [66006, 65420]],
      "common_name": {"english": "Dignity of King", "native": "JwaGak"}
    },
    {
      "id": "CON korean 004",
      "lines": [[64238, 64238]],
      "common_name": {"english": "Nomination", "native": "JinHyeon"}
    },
    {
      "id": "CON korean 005",
      "lines": [[65639, 64407]],
      "common_name": {"english": "Gate of Sky", "native": "CheonMun"}
    },
    {
      "id": "CON korean 006",
      "lines": [[64962, 64166]],
      "common_name": {"english": "Equality", "native": "Pyeong"}
    },
    {
      "id": "CON korean 007",
      "lines": [[67927, 67275, 67459]],
      "common_name": {"english": "Helper", "native": "SeopJae"}
    },
    {
      "id": "CON korean 008",
      "lines": [[72125, 71762, 71795]],
      "common_name": {"english": "Helper", "native": "SeopJae"}
    },
    {
      "id": "CON korean 009",
      "lines": [[69673, 69673]],
      "common_name": {"english": "Position of Holy King", "native": "DaeGaak"}
    },
    {
      "id": "CON korean 010",
      "lines": [[70755, 69701, 69427, 69974]],
      "common_name": {"english": "Neck of Dragon", "native": "Hang"}
    },
    {
      "id": "CON korean 011",
      "lines": [[67494, 68269, 68895, 69415, 70306, 70753]],
      "common_name": {"english": "Beheading", "native": "JeolWii"}
    },
    {
      "id": "CON korean 012",
      "lines": [[68933, 71352]],
      "common_name": {"english": "Judge", "native": "DuunWaan"}
    },
    {
      "id": "CON korean 013",
      "lines": [[71075, 71075]],
      "common_name": {"english": "Flutting Flag", "native": "ChoYo"}
    },
    {
      "id": "CON korean 014",
      "lines": [[72105, 71284, 71053]],
      "common_name": {"english": "Javelin of Sky", "native": "GyeongHaa"}
    },
    {
      "id": "CON korean 015",
      "lines": [[70602, 69226, 67480]],
      "common_name": {"english": "Seat for Longevity", "native": "JaeSeok"}
    },
    {
      "id": "CON korean 016",
      "lines": [[69612, 70327, 70400, 69389, 68707, 68498, 69612]],
      "common_name": {"english": "Oar for visitor", "native": "HangJii"}
    },
    {
      "id": "CON korean 017",
      "lines": [[77516, 77516]],
      "common_name": {"english": "Milk of Sky", "native": "CheonYuu"}
    },
    {
      "id": "CON korean 018",
      "lines": [[74785, 76333, 74392, 72622]],
      "common_name": {"english": "House of Queen", "native": "Jeo"}
    },
    {
      "id": "CON korean 019",
      "lines": [[73714, 74857, 72571]],
      "common_name": {"english": "Ancient Chariot", "native": "JinGeo"}
    },
    {
      "id": "CON korean 020",
      "lines": [[76470, 76600]],
      "common_name": {"english": "Carriage for King", "native": "CheonPouk"}
    },
    {
      "id": "CON korean 021",
      "lines": [[71860, 71860]],
      "common_name": {"english": "General of Cavalry", "native": "GiJinJangGuun"}
    },
    {
      "id": "CON korean 022",
      "lines": [[60718, 60260, 61084, 59196, 60823, 61932, 66657, 70069, 70069, 70264, 63003], [62434, 61084, 59747], [66657, 68523, 68282, 67472, 65109, 64408, 62896, 61932], [62896, 61932], [70069, 74395, 74376, 74911], [70264, 74824]],
      "common_name": {"english": "Cavalry of Emperor", "native": "GiGwan"}
    },
    {
      "id": "CON korean 023",
      "lines": [[71683, 71908, 68702, 71683]],
      "common_name": {"english": "General of Mobile Troops", "native": "GeoGii"}
    },
    {
      "id": "CON korean 024",
      "lines": [[80815, 80473, 80975, 80343]],
      "common_name": {"english": "East Road", "native": "DongHaam"}
    },
    {
      "id": "CON korean 025",
      "lines": [[79374, 79374]],
      "common_name": {"english": "Gate Bolt", "native": "GeonPae"}
    },
    {
      "id": "CON korean 026",
      "lines": [[78820, 78933, 78990]],
      "common_name": {"english": "Door Lock and Key", "native": "GuGeom"}
    },
    {
      "id": "CON korean 027",
      "lines": [[79788, 79599, 79524]],
      "common_name": {"english": "Penalty", "native": "Beol"}
    },
    {
      "id": "CON korean 028",
      "lines": [[78820, 78401, 78265, 78104]],
      "common_name": {"english": "Royal Hall", "native": "Baang"}
    },
    {
      "id": "CON korean 029",
      "lines": [[78105, 77634]],
      "common_name": {"english": "Chamberlain", "native": "JongGwan"}
    },
    {
      "id": "CON korean 030",
      "lines": [[77840, 77840]],
      "common_name": {"english": "Sun", "native": "iil"}
    },
    {
      "id": "CON korean 031",
      "lines": [[79375, 78727, 78207, 77853]],
      "common_name": {"english": "West Road", "native": "SeoHaam"}
    },
    {
      "id": "CON korean 032",
      "lines": [[81266, 80763, 80112]],
      "common_name": {"english": "Seat of Emperor", "native": "Shim"}
    },
    {
      "id": "CON korean 033",
      "lines": [[76297, 75141, 75264, 76829, 76297, 78384], [78639, 76829, 78914], [73273, 75264, 73807], [75177, 75141]],
      "common_name": {"english": "Five Troops", "native": "JeokJol"}
    },
    {
      "id": "CON korean 034",
      "lines": [[85755, 85340, 84970, 84405]],
      "common_name": {"english": "River of Sky", "native": "CheonGang"}
    },
    {
      "id": "CON korean 035",
      "lines": [[87261, 87261]],
      "common_name": {"english": "Prayer for Progeny", "native": "BuYeol"}
    },
    {
      "id": "CON korean 036",
      "lines": [[87569, 87569]],
      "common_name": {"english": "Fish", "native": "Eo"}
    },
    {
      "id": "CON korean 037",
      "lines": [[86092, 87846, 89112, 88714, 85792, 86092]],
      "common_name": {"english": "Forcast", "native": "Ku"}
    },
    {
      "id": "CON korean 038",
      "lines": [[82396, 82514, 82729, 84143, 86228, 87073, 86670, 85927, 85696]],
      "common_name": {"english": "Yard for Empresses", "native": "Mii"}
    },
    {
      "id": "CON korean 039",
      "lines": [[82545, 82514]],
      "common_name": {"english": "Holy Palace", "native": "ShinGuung"}
    },
    {
      "id": "CON korean 040",
      "lines": [[88635, 89931, 90185, 89642]],
      "common_name": {"english": "Winnow", "native": "Kii"}
    },
    {
      "id": "CON korean 041",
      "lines": [[90830, 90414, 90568]],
      "common_name": {"english": "Outer Pestle", "native": "WaeJeo"}
    },
    {
      "id": "CON korean 042",
      "lines": [[90422, 90422]],
      "common_name": {"english": "Chaff", "native": "Gaang"}
    },
    {
      "id": "CON korean 043",
      "lines": [[93526, 93805, 93429, 93026, 92175, 92202, 91845, 91726, 91117]],
      "common_name": {"english": "Head of Town", "native": "CheonByeon"}
    },
    {
      "id": "CON korean 044",
      "lines": [[95176, 95168, 94820], [94141, 93683, 93085]],
      "common_name": {"english": "Build", "native": "Geon"}
    },
    {
      "id": "CON korean 045",
      "lines": [[96483, 96327]],
      "common_name": {"english": "Fowl of Sky", "native": "CheonGae"}
    },
    {
      "id": "CON korean 046",
      "lines": [[89341, 90496, 92041, 92855, 93864, 93506]],
      "common_name": {"english": "Shrine of Sky", "native": "NaamDoo"}
    },
    {
      "id": "CON korean 047",
      "lines": [[93667, 93134]],
      "common_name": {"english": "Dog", "native": "Goo"}
    },
    {
      "id": "CON korean 048",
      "lines": [[96950, 97290, 96465, 95477]],
      "common_name": {"english": "Northeastern Nations", "native": "GuuGuuk"}
    },
    {
      "id": "CON korean 049",
      "lines": [[89678, 89678]],
      "common_name": {"english": "Old Farmer", "native": "NongJaang_iin"}
    },
    {
      "id": "CON korean 050",
      "lines": [[92953, 92308, 91494, 90982, 90887, 91875, 92989, 93174, 93825, 94114, 94160, 94005, 93542, 92953]],
      "common_name": {"english": "Snapping Turtle", "native": "Byeol"}
    },
    {
      "id": "CON korean 051",
      "lines": [[100587, 98110, 97118, 92862]],
      "common_name": {"english": "Road for Emperor", "native": "YeonDo"}
    },
    {
      "id": "CON korean 052",
      "lines": [[91919, 91262, 91971]],
      "common_name": {"english": "The Weaver", "native": "JikNyeo"}
    },
    {
      "id": "CON korean 053",
      "lines": [[93194, 92420, 92791, 94481]],
      "common_name": {"english": "River adjoining Tower", "native": "JaamDae"}
    },
    {
      "id": "CON korean 054",
      "lines": [[99742, 98754, 98819, 98438, 98738, 98337, 97365, 96837], [97365, 96757]],
      "common_name": {"english": "Left Flag", "native": "JwaGi"}
    },
    {
      "id": "CON korean 055",
      "lines": [[97278, 97649, 98036]],
      "common_name": {"english": "Drum of River", "native": "HaGo"}
    },
    {
      "id": "CON korean 056",
      "lines": [[97675, 97938, 98823]],
      "common_name": {"english": "Drumstick of Sky", "native": "CheonBu"}
    },
    {
      "id": "CON korean 057",
      "lines": [[96229, 95501], [96665, 95501, 95585, 96468, 97804, 99473]],
      "common_name": {"english": "Right Flag", "native": "UuGi"}
    },
    {
      "id": "CON korean 058",
      "lines": [[100064, 100345, 101027, 101123, 100881, 100345, 100310]],
      "common_name": {"english": "Cow leading Man", "native": "GyeonUu"}
    },
    {
      "id": "CON korean 059",
      "lines": [[101923, 102026, 101984]],
      "common_name": {"english": "Bank Spread", "native": "NaaEon"}
    },
    {
      "id": "CON korean 060",
      "lines": [[91755, 92512, 90905], [90156, 92512, 91315, 90344], [89348, 91315]],
      "common_name": {"english": "Basket for Silkworm", "native": "BuuGwang"}
    },
    {
      "id": "CON korean 061",
      "lines": [[94779, 95853, 96441, 92689]],
      "common_name": {"english": "Officer for Cart", "native": "HaeJuung"}
    },
    {
      "id": "CON korean 062",
      "lines": [[104732, 105138, 104887, 103413, 102098, 99675, 97165, 100453, 102488, 104732]],
      "common_name": {"english": "Ferry of Sky", "native": "CheonJin"}
    },
    {
      "id": "CON korean 063",
      "lines": [[102532, 101958, 101769, 102281, 102532], [101769, 101589]],
      "common_name": {"english": "Fruit", "native": "Gwa"}
    },
    {
      "id": "CON korean 064",
      "lines": [[103294, 101483, 101800, 101916, 101421, 101483]],
      "common_name": {"english": "Seed", "native": "PaeGwa"}
    },
    {
      "id": "CON korean 065",
      "lines": [[101936, 101847, 101692, 101101]],
      "common_name": {"english": "Storage for Lady", "native": "iiJuu"}
    },
    {
      "id": "CON korean 066",
      "lines": [[102624, 103005, 103045, 102618]],
      "common_name": {"english": "Court Lady", "native": "SuuNyeo"}
    },
    {
      "id": "CON korean 067",
      "lines": [[112917, 111944]],
      "common_name": {"english": "Judge Fault", "native": "SaaBii"}
    },
    {
      "id": "CON korean 068",
      "lines": [[112242, 111104]],
      "common_name": {"english": "Amend Fault", "native": "SaaWii"}
    },
    {
      "id": "CON korean 069",
      "lines": [[111841, 109754]],
      "common_name": {"english": "Grant Life", "native": "SaaRok"}
    },
    {
      "id": "CON korean 070",
      "lines": [[104858, 104521]],
      "common_name": {"english": "Punish", "native": "SaaMyeong"}
    },
    {
      "id": "CON korean 071",
      "lines": [[104987, 106278]],
      "common_name": {"english": "Empty House", "native": "Heo"}
    },
    {
      "id": "CON korean 072",
      "lines": [[106786, 107382]],
      "common_name": {"english": "Weep", "native": "Gok"}
    },
    {
      "id": "CON korean 073",
      "lines": [[107517, 107095]],
      "common_name": {"english": "Sob", "native": "Eup"}
    },
    {
      "id": "CON korean 074",
      "lines": [[104139, 104019, 104365, 104963, 105515, 104974, 104139]],
      "common_name": {"english": "Castle with Rampart", "native": "CheonRuSeong"}
    },
    {
      "id": "CON korean 075",
      "lines": [[107418, 107259, 107136, 107533, 106481, 105186, 104060, 104194]],
      "common_name": {"english": "Hook for Dress", "native": "Guu"}
    },
    {
      "id": "CON korean 076",
      "lines": [[109592, 110991, 109556], [109492, 110991, 109857]],
      "common_name": {"english": "Groom", "native": "ChoBo"}
    },
    {
      "id": "CON korean 077",
      "lines": [[107235, 106711, 106551, 107253, 107235, 109102, 110351, 111022]],
      "common_name": {"english": "Office for Chariots", "native": "GeoBuu"}
    },
    {
      "id": "CON korean 078",
      "lines": [[106140, 107472, 108060], [107348, 107472, 105502]],
      "common_name": {"english": "Human", "native": "iinSeong"}
    },
    {
      "id": "CON korean 079",
      "lines": [[109937, 109410]],
      "common_name": {"english": "Inner Pestle", "native": "NaeJeo"}
    },
    {
      "id": "CON korean 080",
      "lines": [[110371, 109176, 107354, 107310]],
      "common_name": {"english": "Mortar", "native": "Gu"}
    },
    {
      "id": "CON korean 081",
      "lines": [[107315, 109427, 109074]],
      "common_name": {"english": "Warehouse of Sky", "native": "Wii"}
    },
    {
      "id": "CON korean 082",
      "lines": [[110672, 110960, 110395], [110960, 111497]],
      "common_name": {"english": "Tomb", "native": "BunMyo"}
    },
    {
      "id": "CON korean 083",
      "lines": [[108874, 110003]],
      "common_name": {"english": "Cover of House", "native": "GaeOok"}
    },
    {
      "id": "CON korean 084",
      "lines": [[102485, 102978, 105881, 105665]],
      "common_name": {"english": "Broken Mortar", "native": "PaeGuu"}
    },
    {
      "id": "CON korean 085",
      "lines": [[115990, 114622, 113561, 114104, 115990, 117301, 117863, 118243, 114924, 113919, 114570, 115022, 116584, 116805, 116631, 113726], [113288, 113919, 113327]],
      "common_name": {"english": "Climbing Serpent", "native": "DeungSaa"}
    },
    {
      "id": "CON korean 086",
      "lines": [[113881, 113963], [113881, 112158, 112051], [113881, 112748, 112440], [113881, 115250, 115623]],
      "common_name": {"english": "Palace of Emperor", "native": "Shil"}
    },
    {
      "id": "CON korean 087",
      "lines": [[115250, 115250]],
      "common_name": {"english": "Detached Palace", "native": "iiGuung"}
    },
    {
      "id": "CON korean 088",
      "lines": [[112447, 112029]],
      "common_name": {"english": "Official for Material Supply", "native": "TouGongRi"}
    },
    {
      "id": "CON korean 089",
      "lines": [[114389, 114144, 114520], [114144, 113186, 112935]],
      "common_name": {"english": "Lightening", "native": "JeonNwoe"}
    },
    {
      "id": "CON korean 090",
      "lines": [[112961, 111123, 109139, 107556, 106985, 106723, 107188, 107556]],
      "common_name": {"english": "Rampart", "native": "NuByeokJin"}
    },
    {
      "id": "CON korean 091",
      "lines": [[1170, 983, 301, 910, 355, 117567, 116971, 116957, 116901, 117218, 117629], [355, 1158, 443, 145], [664, 145, 118209], [840, 443, 154], [116971, 116591, 116853, 117314, 117541], [116591, 115115, 115033, 114855, 114939, 114724, 113996], [115115, 115125, 115404, 115438, 115669, 116247], [115126, 112716, 112211, 112529, 114341, 114375, 114119], [115142, 114724]],
      "common_name": {"english": "Troops of Sky", "native": "URimGuun"}
    },
    {
      "id": "CON korean 092",
      "lines": [[113368, 113368]],
      "common_name": {"english": "Village for Patrol", "native": "BukRakSaMuun"}
    },
    {
      "id": "CON korean 093",
      "lines": [[111954, 111954]],
      "common_name": {"english": "Net of Sky", "native": "CheonMang"}
    },
    {
      "id": "CON korean 094",
      "lines": [[101076, 99874, 99824, 99951, 100435, 101868, 102388, 103004, 103200, 102453, 101076]],
      "common_name": {"english": "Stable of Sky", "native": "CheonGu"}
    },
    {
      "id": "CON korean 095",
      "lines": [[1067, 447]],
      "common_name": {"english": "Eastern Wall", "native": "DongByeok"}
    },
    {
      "id": "CON korean 096",
      "lines": [[2219, 3810]],
      "common_name": {"english": "Civil Engineer", "native": "TouGong"}
    },
    {
      "id": "CON korean 097",
      "lines": [[118268, 116771, 115830, 114971, 113889]],
      "common_name": {"english": "Thunderbolts", "native": "ByeokRyeok"}
    },
    {
      "id": "CON korean 098",
      "lines": [[117245, 116928, 115738, 114273]],
      "common_name": {"english": "Clouds and Rain", "native": "UunUu"}
    },
    {
      "id": "CON korean 099",
      "lines": [[3504, 3801, 5542, 6242, 6686, 8886, 11569]],
      "common_name": {"english": "Highway", "native": "GaakDo"}
    },
    {
      "id": "CON korean 100",
      "lines": [[2599, 2599]],
      "common_name": {"english": "Whip", "native": "Chaek"}
    },
    {
      "id": "CON korean 101",
      "lines": [[4427, 746, 2920], [3821, 746, 3179]],
      "common_name": {"english": "Charioteer of the Emperor", "native": "WaangRaang"}
    },
    {
      "id": "CON korean 102",
      "lines": [[5434, 5434]],
      "common_name": {"english": "Side Road", "native": "BuRo"}
    },
    {
      "id": "CON korean 103",
      "lines": [[3881, 4436, 5447, 5544, 5586, 6193, 5742, 5454, 4463, 3693, 3031, 3092, 2912, 2942, 3231, 3881]],
      "common_name": {"english": "Armory", "native": "Gyu"}
    },
    {
      "id": "CON korean 104",
      "lines": [[8796, 8796]],
      "common_name": {"english": "Southern Gate of Emperator", "native": "GuunNaamMun"}
    },
    {
      "id": "CON korean 105",
      "lines": [[8833, 7884, 7007, 5737, 4906, 3786, 2548]],
      "common_name": {"english": "Outer Folding Screen", "native": "WaeByeong"}
    },
    {
      "id": "CON korean 106",
      "lines": [[6061, 4147, 2762, 4914, 5951, 6061]],
      "common_name": {"english": "Toilet of Sky", "native": "CheonHoun"}
    },
    {
      "id": "CON korean 107",
      "lines": [[3419, 3419]],
      "common_name": {"english": "Architect", "native": "SaaGong"}
    },
    {
      "id": "CON korean 108",
      "lines": [[10340, 9640, 7513, 6813, 7607, 8068], [9640, 9977, 10064, 10670, 12086]],
      "common_name": {"english": "Emperator", "native": "CheonJaangGuun"}
    },
    {
      "id": "CON korean 109",
      "lines": [[9884, 8903, 8832]],
      "common_name": {"english": "Watchtower", "native": "Ruu"}
    },
    {
      "id": "CON korean 110",
      "lines": [[12332, 10306, 10732], [10306, 10155, 10328, 10732]],
      "common_name": {"english": "Left Elm", "native": "JwaGyeong"}
    },
    {
      "id": "CON korean 111",
      "lines": [[9110, 7447, 7097, 7535, 7740, 7447]],
      "common_name": {"english": "Right Elm", "native": "UuGyeong"}
    },
    {
      "id": "CON korean 112",
      "lines": [[1562, 5364, 6537, 8645, 8102, 9347]],
      "common_name": {"english": "Storehouse of Sky", "native": "CheonChang"}
    },
    {
      "id": "CON korean 113",
      "lines": [[8209, 7679, 6960, 8209]],
      "common_name": {"english": "Stack of Cereals", "native": "CheonYu"}
    },
    {
      "id": "CON korean 114",
      "lines": [[19949, 20070, 19812, 19343, 17358, 16826, 15863, 14328, 13268]],
      "common_name": {"english": "Ship of Sky", "native": "CheonSeon"}
    },
    {
      "id": "CON korean 115",
      "lines": [[19167, 19167]],
      "common_name": {"english": "Store of Water", "native": "JeokSuu"}
    },
    {
      "id": "CON korean 116",
      "lines": [[9505, 13531, 14632, 14668, 14576, 14354, 13254, 12623]],
      "common_name": {"english": "Mausoleum", "native": "DaeReung"}
    },
    {
      "id": "CON korean 117",
      "lines": [[12621, 12621]],
      "common_name": {"english": "Heap of Corpse", "native": "JeokShi"}
    },
    {
      "id": "CON korean 118",
      "lines": [[13209, 13061, 12719, 13209]],
      "common_name": {"english": "Stomach of Tiger", "native": "Wii"}
    },
    {
      "id": "CON korean 119",
      "lines": [[16369, 16322, 16083, 15900]],
      "common_name": {"english": "Store of Millet for Offering", "native": "CheonReum"}
    },
    {
      "id": "CON korean 120",
      "lines": [[13954, 12828, 11484, 10324, 9487, 9589, 10305, 11791, 12387, 12706, 14135, 15457, 16852]],
      "common_name": {"english": "Storehouse for Cereals", "native": "CheonGyun"}
    },
    {
      "id": "CON korean 121",
      "lines": [[20354, 21476, 22453, 22678]],
      "common_name": {"english": "Whetstone", "native": "RyeoSeok"}
    },
    {
      "id": "CON korean 122",
      "lines": [[17529, 18532, 18614, 18246, 17448, 17313]],
      "common_name": {"english": "Rolled Tongue", "native": "GwonSeol"}
    },
    {
      "id": "CON korean 123",
      "lines": [[17886, 17886]],
      "common_name": {"english": "Shaman of Sky", "native": "CheonCham"}
    },
    {
      "id": "CON korean 124",
      "lines": [[17847, 17702, 17608, 17499, 17573, 17702], [17573, 17531, 17489, 17499]],
      "common_name": {"english": "Ear and Eye of the Sky", "native": "Myo"}
    },
    {
      "id": "CON korean 125",
      "lines": [[19038, 19038]],
      "common_name": {"english": "Moon", "native": "Wol"}
    },
    {
      "id": "CON korean 126",
      "lines": [[21881, 21881]],
      "common_name": {"english": "Hill of Sky", "native": "CheonAa"}
    },
    {
      "id": "CON korean 127",
      "lines": [[19799, 20522, 19740], [19860, 20522, 19719]],
      "common_name": {"english": "Conspiracy of Sky", "native": "CheonEum"}
    },
    {
      "id": "CON korean 128",
      "lines": [[12107, 12390, 11345, 11783]],
      "common_name": {"english": "Fodder", "native": "ChuuGo"}
    },
    {
      "id": "CON korean 129",
      "lines": [[21248, 21393, 20535, 20042, 17874, 17797, 17351, 16870, 15510, 13847, 12486, 11477, 13147, 14879]],
      "common_name": {"english": "Hill of Sky", "native": "Cheonwon"}
    },
    {
      "id": "CON korean 130",
      "lines": [[28360, 24608, 23015, 25428, 28380, 28360]],
      "common_name": {"english": "Garage for Chariot", "native": "OoGeo"}
    },
    {
      "id": "CON korean 131",
      "lines": [[25048, 24813, 24340]],
      "common_name": {"english": "Pond for Fish", "native": "HaamJii"}
    },
    {
      "id": "CON korean 132",
      "lines": [[23767, 23416, 23453]],
      "common_name": {"english": "Pillar", "native": "Ju"}
    },
    {
      "id": "CON korean 133",
      "lines": [[27673, 27639, 27483]],
      "common_name": {"english": "Pillar", "native": "Ju"}
    },
    {
      "id": "CON korean 134",
      "lines": [[25984, 26536, 25492]],
      "common_name": {"english": "Pillar", "native": "Ju"}
    },
    {
      "id": "CON korean 135",
      "lines": [[24879, 24575, 24799], [24727, 24575, 24504]],
      "common_name": {"english": "Puddle of Sky", "native": "CheonHwang"}
    },
    {
      "id": "CON korean 136",
      "lines": [[17954, 19171, 20250, 20430, 23088, 23900]],
      "common_name": {"english": "Kings", "native": "JaeWaang"}
    },
    {
      "id": "CON korean 137",
      "lines": [[26451, 26451]],
      "common_name": {"english": "Gateway of Sky", "native": "CheonGwan"}
    },
    {
      "id": "CON korean 138",
      "lines": [[23607, 22957, 22833, 22845, 22509, 22449, 22549, 22797, 23123]],
      "common_name": {"english": "Flage of Saam", "native": "SaamGii"}
    },
    {
      "id": "CON korean 139",
      "lines": [[20711, 19990]],
      "common_name": {"english": "Village of Sky", "native": "CheonGa"}
    },
    {
      "id": "CON korean 140",
      "lines": [[26777, 25945, 25278, 25555, 26777]],
      "common_name": {"english": "Belvedere of Sky", "native": "CheonGo"}
    },
    {
      "id": "CON korean 141",
      "lines": [[20889, 20648, 20455, 20205, 18724], [20205, 20713, 21029, 21421, 21683]],
      "common_name": {"english": "General of Border", "native": "Piil"}
    },
    {
      "id": "CON korean 142",
      "lines": [[21273, 20732, 20219], [20732, 20901, 21589, 21402, 21670]],
      "common_name": {"english": "Imperial credentials", "native": "CheonJeol"}
    },
    {
      "id": "CON korean 143",
      "lines": [[23166, 22881, 22479, 22325, 22263, 22028, 21763, 22086]],
      "common_name": {"english": "Flag of Emperor", "native": "GuuYuu"}
    },
    {
      "id": "CON korean 144",
      "lines": [[22109, 22701, 22024, 21297, 19849, 19587, 20507, 21444, 21547, 22109]],
      "common_name": {"english": "Nine Territory", "native": "GuJuJuGu"}
    },
    {
      "id": "CON korean 145",
      "lines": [[18543, 17593, 17378, 16537, 15197, 13701, 12770, 12843, 13288, 14146, 15474, 16611, 17651, 18216, 18673]],
      "common_name": {"english": "Garden of Sky", "native": "CheonWon"}
    },
    {
      "id": "CON korean 146",
      "lines": [[29696, 28237, 27830, 27468, 26248, 25539, 24822, 23497]],
      "common_name": {"english": "Settled Flag", "native": "JwaGii"}
    },
    {
      "id": "CON korean 147",
      "lines": [[29650, 28716, 27913]],
      "common_name": {"english": "Forecast Calamity", "native": "SaaGwae"}
    },
    {
      "id": "CON korean 148",
      "lines": [[30122, 30277]],
      "common_name": {"english": "Son", "native": "Za"}
    },
    {
      "id": "CON korean 149",
      "lines": [[27989, 26727, 26311, 25930, 24436], [25930, 25336], [26727, 27366]],
      "common_name": {"english": "Saam", "native": "Saam"}
    },
    {
      "id": "CON korean 150",
      "lines": [[26311, 26237, 26221, 26241]],
      "common_name": {"english": "Expeditionary Force", "native": "Beol"}
    },
    {
      "id": "CON korean 151",
      "lines": [[24244, 24327, 24845, 24873]],
      "common_name": {"english": "Well for Military", "native": "GuunJeong"}
    },
    {
      "id": "CON korean 152",
      "lines": [[24674, 23875, 23364, 23972]],
      "common_name": {"english": "Well of Jade", "native": "OkJeong"}
    },
    {
      "id": "CON korean 153",
      "lines": [[24305, 23685]],
      "common_name": {"english": "Folding Screen", "native": "Byeong"}
    },
    {
      "id": "CON korean 154",
      "lines": [[25985, 25606, 27072, 27654]],
      "common_name": {"english": "Toilet", "native": "Cheuk"}
    },
    {
      "id": "CON korean 155",
      "lines": [[25859, 25859]],
      "common_name": {"english": "Arrow", "native": "Shii"}
    },
    {
      "id": "CON korean 156",
      "lines": [[37265, 37265]],
      "common_name": {"english": "Piled Brushwood", "native": "JeokShin"}
    },
    {
      "id": "CON korean 157",
      "lines": [[36145, 36145]],
      "common_name": {"english": "Store of Water", "native": "JeokSuu"}
    },
    {
      "id": "CON korean 158",
      "lines": [[37826, 36850, 36366]],
      "common_name": {"english": "Northern River", "native": "BuukHa"}
    },
    {
      "id": "CON korean 159",
      "lines": [[37740, 36962, 36046, 34693, 33018]],
      "common_name": {"english": "Five Lords", "native": "OJeHuu"}
    },
    {
      "id": "CON korean 160",
      "lines": [[35550, 37908, 36760, 35550]],
      "common_name": {"english": "Wine Glass of Sky", "native": "CheonJuun"}
    },
    {
      "id": "CON korean 161",
      "lines": [[35350, 34088, 32921, 32246], [32921, 30883, 30343], [30883, 31681, 34088], [31681, 32362], [30343, 29655]],
      "common_name": {"english": "Eastern Well", "native": "DongJeong"}
    },
    {
      "id": "CON korean 162",
      "lines": [[29704, 29434, 29038, 29426, 29704]],
      "common_name": {"english": "Flood control", "native": "SuuBuu"}
    },
    {
      "id": "CON korean 163",
      "lines": [[40526, 40526]],
      "common_name": {"english": "Balance of Water", "native": "SuuWii"}
    },
    {
      "id": "CON korean 164",
      "lines": [[33202, 31978, 31216, 30419]],
      "common_name": {"english": "Four Spirit of River", "native": "SaaDok"}
    },
    {
      "id": "CON korean 165",
      "lines": [[37279, 36188, 36284]],
      "common_name": {"english": "Southern River", "native": "NamHa"}
    },
    {
      "id": "CON korean 166",
      "lines": [[39311, 34769]],
      "common_name": {"english": "Twin Gate", "native": "GwolGu"}
    },
    {
      "id": "CON korean 167",
      "lines": [[37819, 34444, 38901, 37819, 36377, 35264, 35904, 38170, 39906, 38901]],
      "common_name": {"english": "Bow", "native": "Ho"}
    },
    {
      "id": "CON korean 168",
      "lines": [[32349, 32349]],
      "common_name": {"english": "Star of Wolf", "native": "RangSeong"}
    },
    {
      "id": "CON korean 169",
      "lines": [[30324, 30324]],
      "common_name": {"english": "Wild Fowls", "native": "YaGae"}
    },
    {
      "id": "CON korean 170",
      "lines": [[31592, 31827, 31084, 30457, 28910, 28816, 29048, 29941, 31592]],
      "common_name": {"english": "Market for Army", "native": "GuunShii"}
    },
    {
      "id": "CON korean 171",
      "lines": [[33579, 32759]],
      "common_name": {"english": "Grandchildren", "native": "Soun"}
    },
    {
      "id": "CON korean 172",
      "lines": [[26207, 26176, 26366, 26207]],
      "common_name": {"english": "Scout of Three Troups", "native": "Zaa"}
    },
    {
      "id": "CON korean 173",
      "lines": [[26634, 27628]],
      "common_name": {"english": "Grown-up", "native": "Zaang_iin"}
    },
    {
      "id": "CON korean 174",
      "lines": [[30438, 30438]],
      "common_name": {"english": "Oldman", "native": "Noin"}
    },
    {
      "id": "CON korean 175",
      "lines": [[43103, 43834, 44818, 44154, 43103]],
      "common_name": {"english": "Beacon", "native": "Gwan"}
    },
    {
      "id": "CON korean 176",
      "lines": [[42806, 42911, 41822, 41909, 42806]],
      "common_name": {"english": "Eye of Sky", "native": "Kwii"}
    },
    {
      "id": "CON korean 177",
      "lines": [[42516, 42516]],
      "common_name": {"english": "Pile of Dead", "native": "JeokShii"}
    },
    {
      "id": "CON korean 178",
      "lines": [[51849, 51232, 50371, 51576, 52468, 53253, 52742, 51849]],
      "common_name": {"english": "Green Ridge", "native": "CheonGu"}
    },
    {
      "id": "CON korean 179",
      "lines": [[41307, 39863, 39079, 38474, 37901, 37447]],
      "common_name": {"english": "Outer Kitchen", "native": "WaeJuu"}
    },
    {
      "id": "CON korean 180",
      "lines": [[30772, 30867, 29651]],
      "common_name": {"english": "Dog of Sky", "native": "CheonGu"}
    },
    {
      "id": "CON korean 181",
      "lines": [[39953, 42570, 42913, 45941], [42913, 41037], [42570, 44816]],
      "common_name": {"english": "Spirit of GuRyoung", "native": "CheonSa"}
    },
    {
      "id": "CON korean 182",
      "lines": [[44066, 44798, 45410, 44066]],
      "common_name": {"english": "Flag of Wine Officer", "native": "JuuGii"}
    },
    {
      "id": "CON korean 183",
      "lines": [[45336, 44659, 43813, 43109, 42313, 42402, 42799, 43234]],
      "common_name": {"english": "Officer of Kitchen", "native": "Ryu"}
    },
    {
      "id": "CON korean 184",
      "lines": [[48833, 47029, 49593], [47029, 46952]],
      "common_name": {"english": "Equality and Fair", "native": "NaePyeong"}
    },
    {
      "id": "CON korean 185",
      "lines": [[41075, 43531, 44248, 44700, 45688, 45860, 46146, 46750, 47908, 48455, 50335, 50583, 49583, 49669, 47508], [49669, 51624], [49669, 49637]],
      "common_name": {"english": "Emperor HeonWon", "native": "HeonWon"}
    },
    {
      "id": "CON korean 186",
      "lines": [[47431, 46776, 46509, 46404, 46390, 45811, 45751]],
      "common_name": {"english": "Capital of Sky", "native": "Seong"}
    },
    {
      "id": "CON korean 187",
      "lines": [[43409, 42828, 46651, 42312, 39429, 42828]],
      "common_name": {"english": "Chief of Farming", "native": "Jiik"}
    },
    {
      "id": "CON korean 188",
      "lines": [[52085, 51069, 49841, 49402, 48356, 47452], [48356, 48615, 51069]],
      "common_name": {"english": "Officer of Tomb", "native": "Jaang"}
    },
    {
      "id": "CON korean 189",
      "lines": [[46880, 46371, 45902, 44824, 45001, 46026, 46578, 47187, 47758, 48559, 48584, 47522, 46880]],
      "common_name": {"english": "Tomb of Sky", "native": "CheonMyo"}
    },
    {
      "id": "CON korean 190",
      "lines": [[55282, 55705, 54682, 53740, 55282], [53740, 52943], [55705, 57283], [55282, 54029, 55687, 56802], [55687, 56633, 58576], [54682, 54204, 54477, 56280], [54204, 51172, 53502, 55756, 56922, 57936]],
      "common_name": {"english": "Wing of Red Bird", "native": "iik"}
    },
    {
      "id": "CON korean 191",
      "lines": [[52727, 51986, 51635, 51561, 50191]],
      "common_name": {"english": "Eastern Pottery", "native": "DonGu"}
    },
    {
      "id": "CON korean 192",
      "lines": [[61359, 60965, 59803, 59316, 59199], [61359, 59316], [60965, 61174]],
      "common_name": {"english": "Chariot of Emperor", "native": "Jin"}
    },
    {
      "id": "CON korean 193",
      "lines": [[60189, 59316]],
      "common_name": {"english": "Sand for Life", "native": "JangSaa"}
    },
    {
      "id": "CON korean 194",
      "lines": [[56480, 55425]],
      "common_name": {"english": "Gateway for Troops", "native": "GuunMuun"}
    },
    {
      "id": "CON korean 195",
      "lines": [[52419, 54301, 54751, 54463]],
      "common_name": {"english": "Civil Engineer", "native": "TouSaaGong"}
    },
    {
      "id": "CON korean 196",
      "lines": [[63125, 63125]],
      "common_name": {"english": "Guardian Knight", "native": "NangJaang"}
    },
    {
      "id": "CON korean 197",
      "lines": [[44127, 44471, 50372, 50801, 55219, 55203]],
      "common_name": {"english": "Three Steps", "native": "SaamTae"}
    },
    {
      "id": "CON korean 198",
      "lines": [[59819, 60202, 61418, 62886, 64394]],
      "common_name": {"english": "Five Feudal Lords", "native": "OZehu"}
    },
    {
      "id": "CON korean 199",
      "lines": [[61394, 60941, 60746, 60742], [60746, 60351, 59847]],
      "common_name": {"english": "SangJiin", "native": "SangJiin"}
    },
    {
      "id": "CON korean 200",
      "lines": [[53954, 53417, 52098, 51233]],
      "common_name": {"english": "Low Fence", "native": "SoMii"}
    },
    {
      "id": "CON korean 201",
      "lines": [[54872, 54879, 55642, 55434, 57757]],
      "common_name": {"english": "Tall Fence", "native": "TaeMi"}
    },
    {
      "id": "CON korean 202",
      "lines": [[64241, 63608, 63090, 61941, 60129]],
      "common_name": {"english": "Tall Fence", "native": "TaeMi"}
    },
    {
      "id": "CON korean 203",
      "lines": [[63355, 62807, 62356]],
      "common_name": {"english": "Nine Lords", "native": "GuGyeong"}
    },
    {
      "id": "CON korean 204",
      "lines": [[54951, 54951]],
      "common_name": {"english": "Dung of Tiger", "native": "HoBuun"}
    },
    {
      "id": "CON korean 205",
      "lines": [[57565, 57565]],
      "common_name": {"english": "Crown Prince", "native": "TeaJaa"}
    },
    {
      "id": "CON korean 206",
      "lines": [[56975, 56975]],
      "common_name": {"english": "Chamberlain", "native": "JongGwan"}
    },
    {
      "id": "CON korean 207",
      "lines": [[57632, 58159]],
      "common_name": {"english": "Five Emperor", "native": "OJe"}
    },
    {
      "id": "CON korean 208",
      "lines": [[58948, 58590, 57380, 57328]],
      "common_name": {"english": "Folding Screen", "native": "Byeong"}
    },
    {
      "id": "CON korean 209",
      "lines": [[62325, 61960, 62267, 62325]],
      "common_name": {"english": "Three Minister", "native": "SaamGongNaeJwa"}
    },
    {
      "id": "CON korean 210",
      "lines": [[60172, 60172]],
      "common_name": {"english": "Officer for Audience", "native": "AlZaa"}
    },
    {
      "id": "CON korean 211",
      "lines": [[56647, 56127, 55084]],
      "common_name": {"english": "Grave Front", "native": "MyeongDang"}
    },
    {
      "id": "CON korean 212",
      "lines": [[54182, 53807, 53907]],
      "common_name": {"english": "Observatory", "native": "YeongDae"}
    },
    {
      "id": "CON korean 213",
      "lines": [[80480, 81854, 79822, 78661, 80480]],
      "common_name": {"english": "Female Officer", "native": "YeoEoGwan"}
    },
    {
      "id": "CON korean 214",
      "lines": [[9598, 115088, 113864, 112724, 108917, 105199, 102422]],
      "common_name": {"english": "Wide Lodging Area", "native": "JeonSaa"}
    },
    {
      "id": "CON korean 215",
      "lines": [[22783, 29997, 33449, 28358, 25197, 23522, 22783], [25197, 23040, 23783]],
      "common_name": {"english": "Eight Cereals", "native": "PalGok"}
    },
    {
      "id": "CON korean 216",
      "lines": [[87585, 85819, 85670, 87833, 86414]],
      "common_name": {"english": "Advance Guard", "native": "CheonBae"}
    },
    {
      "id": "CON korean 217",
      "lines": [[66234, 64906, 65550, 66234]],
      "common_name": {"english": "Three Ministers", "native": "SamGong"}
    },
    {
      "id": "CON korean 218",
      "lines": [[52353, 51448, 50933, 52353]],
      "common_name": {"english": "Three Ministers", "native": "SamGong"}
    },
    {
      "id": "CON korean 219",
      "lines": [[67301, 65378, 62956, 59774, 58001, 53910, 54061]],
      "common_name": {"english": "Northern Dipper", "native": "BukDuu"}
    },
    {
      "id": "CON korean 220",
      "lines": [[65477, 65477]],
      "common_name": {"english": "Helper", "native": "Bo"}
    },
    {
      "id": "CON korean 221",
      "lines": [[74605, 73199]],
      "common_name": {"english": "Virtue", "native": "EumDeok"}
    },
    {
      "id": "CON korean 222",
      "lines": [[61384, 61384]],
      "common_name": {"english": "Emperor's God of War", "native": "Cheon_iil"}
    },
    {
      "id": "CON korean 223",
      "lines": [[60998, 60998]],
      "common_name": {"english": "Emperor's God of Weather", "native": "Tae_iil"}
    },
    {
      "id": "CON korean 224",
      "lines": [[63432, 63076]],
      "common_name": {"english": "Inner Kitchen", "native": "NaeJuu"}
    },
    {
      "id": "CON korean 225",
      "lines": [[73555, 73555]],
      "common_name": {"english": "Flap of Flag", "native": "HyeonGwa"}
    },
    {
      "id": "CON korean 226",
      "lines": [[57399, 57399]],
      "common_name": {"english": "Minister", "native": "Saang"}
    },
    {
      "id": "CON korean 227",
      "lines": [[54539, 54539]],
      "common_name": {"english": "General and Minister", "native": "TaeYaangSuu"}
    },
    {
      "id": "CON korean 228",
      "lines": [[53043, 53261, 52136, 51459, 51814, 52478, 53043]],
      "common_name": {"english": "Jail of Sky", "native": "CheonRyoe"}
    },
    {
      "id": "CON korean 229",
      "lines": [[41704, 45075, 46733, 48319, 48402, 46853, 44901]],
      "common_name": {"english": "Six Department", "native": "MunChang"}
    },
    {
      "id": "CON korean 230",
      "lines": [[47594, 46977, 45038, 44390, 42527, 42080]],
      "common_name": {"english": "Inner Stairway", "native": "NaeGae"}
    },
    {
      "id": "CON korean 231",
      "lines": [[69713, 70497, 69483]],
      "common_name": {"english": "Spear of Sky", "native": "CheonChang"}
    },
    {
      "id": "CON korean 232",
      "lines": [[107119, 108535, 106032, 107119, 109400, 111532, 114222, 116727, 108535, 114222], [111532, 108535, 109400]],
      "common_name": {"english": "Cover for Emperor", "native": "HwaGae"}
    },
    {
      "id": "CON korean 233",
      "lines": [[94648, 92056, 89937], [92782, 92056, 92112]],
      "common_name": {"english": "Place for Five Emperor", "native": "OJeJwa"}
    },
    {
      "id": "CON korean 234",
      "lines": [[99255, 99255]],
      "common_name": {"english": "60 Years", "native": "YuukGaap"}
    },
    {
      "id": "CON korean 235",
      "lines": [[95081, 98702, 97433, 96100, 94376, 95081]],
      "common_name": {"english": "Kitchen of Sky", "native": "CheonJu"}
    },
    {
      "id": "CON korean 236",
      "lines": [[75097, 72607, 70692, 69112, 62572]],
      "common_name": {"english": "North Pole", "native": "BukGeuk"}
    },
    {
      "id": "CON korean 237",
      "lines": [[112519, 5372, 11767, 85822, 82080, 77055]],
      "common_name": {"english": "Wound Lodge", "native": "GuJiin"}
    },
    {
      "id": "CON korean 238",
      "lines": [[102208, 100965, 102599, 104756, 105727, 104105, 104968]],
      "common_name": {"english": "Single-log Bridge", "native": "Gaang"}
    },
    {
      "id": "CON korean 239",
      "lines": [[113116, 113116]],
      "common_name": {"english": "Great Emperor", "native": "CheonHwangTaeJae"}
    },
    {
      "id": "CON korean 240",
      "lines": [[75974, 77277, 75260], [75256, 77277, 75696]],
      "common_name": {"english": "Officer for Opinion", "native": "SaangSeo"}
    },
    {
      "id": "CON korean 241",
      "lines": [[79414, 79867, 80161], [78893, 79867, 80650, 80161]],
      "common_name": {"english": "Pillar of Sky", "native": "CheonJu"}
    },
    {
      "id": "CON korean 242",
      "lines": [[86614, 86614]],
      "common_name": {"english": "Secretary", "native": "JuHaSa"}
    },
    {
      "id": "CON korean 243",
      "lines": [[87728, 87728]],
      "common_name": {"english": "Maid", "native": "YeoSa"}
    },
    {
      "id": "CON korean 244",
      "lines": [[85112, 84606, 84380]],
      "common_name": {"english": "Desk of Woman", "native": "YeoSaang"}
    },
    {
      "id": "CON korean 245",
      "lines": [[57477, 58181, 56035]],
      "common_name": {"english": "Judge Prison", "native": "DaeRii"}
    },
    {
      "id": "CON korean 246",
      "lines": [[89908, 86201, 83895, 80331, 78527, 75458, 68756]],
      "common_name": {"english": "Purple Fence", "native": "JaMi"}
    },
    {
      "id": "CON korean 247",
      "lines": [[61281, 56211, 52425, 47654, 33694, 25110]],
      "common_name": {"english": "Purple Fence", "native": "JaMi"}
    },
    {
      "id": "CON korean 248",
      "lines": [[90191, 89826, 88836, 89172, 87998, 87933, 86974, 85693, 84379]],
      "common_name": {"english": "Order of Sky", "native": "CheonGii"}
    },
    {
      "id": "CON korean 249",
      "lines": [[81833, 81126, 79992, 79101, 77760, 75411, 74666]],
      "common_name": {"english": "Seven Minister", "native": "ChilGong"}
    },
    {
      "id": "CON korean 250",
      "lines": [[78493, 78159, 77512, 76952, 76267, 75695, 76127]],
      "common_name": {"english": "Thread Straw", "native": "GwanSak"}
    },
    {
      "id": "CON korean 251",
      "lines": [[84012, 86263, 88048, 89962, 91975, 92946, 93747, 92043, 90139, 88886, 88267]],
      "common_name": {"english": "Market Fence", "native": "CheonShi"}
    },
    {
      "id": "CON korean 252",
      "lines": [[80816, 80170, 79043, 78072, 77233, 76276, 77070, 77622, 79593, 79882, 81377]],
      "common_name": {"english": "Market Fence", "native": "CheonShi"}
    },
    {
      "id": "CON korean 253",
      "lines": [[86032, 86032]],
      "common_name": {"english": "Feudal Lord", "native": "Huu"}
    },
    {
      "id": "CON korean 254",
      "lines": [[84345, 84345]],
      "common_name": {"english": "Seat for Emperor", "native": "JaeJwa"}
    },
    {
      "id": "CON korean 255",
      "lines": [[88771, 88765]],
      "common_name": {"english": "Royal Family", "native": "JongSeong"}
    },
    {
      "id": "CON korean 256",
      "lines": [[86742, 87108]],
      "common_name": {"english": "Head of Family", "native": "JongJeong"}
    },
    {
      "id": "CON korean 257",
      "lines": [[88149, 88601, 88290], [88601, 88192]],
      "common_name": {"english": "Record of Family", "native": "Jong_iin"}
    },
    {
      "id": "CON korean 258",
      "lines": [[91217, 91237, 89918, 89772, 91217]],
      "common_name": {"english": "Officer for Family", "native": "JongDaeBuu"}
    },
    {
      "id": "CON korean 259",
      "lines": [[84402, 83962, 86284, 85922, 85365, 84880, 84402]],
      "common_name": {"english": "Tower in Market", "native": "ShiRuu"}
    },
    {
      "id": "CON korean 260",
      "lines": [[80883, 80179, 79488, 80351]],
      "common_name": {"english": "Measure Cereal", "native": "Gok"}
    },
    {
      "id": "CON korean 261",
      "lines": [[83000, 82673, 82073, 82402, 82216]],
      "common_name": {"english": "Cereal Measure Regulation", "native": "Duu"}
    },
    {
      "id": "CON korean 262",
      "lines": [[84671, 84177, 83613, 83430]],
      "common_name": {"english": "Eunuch", "native": "HwanJaa"}
    },
    {
      "id": "CON korean 263",
      "lines": [[84514, 82369]],
      "common_name": {"english": "Officer for Chariots", "native": "GeoSaa"}
    },
    {
      "id": "CON korean 264",
      "lines": [[90067, 88899]],
      "common_name": {"english": "Measure Amount", "native": "BaekTaak"}
    },
    {
      "id": "CON korean 265",
      "lines": [[93244, 92161]],
      "common_name": {"english": "Butchery", "native": "DoSaa"}
    },
    {
      "id": "CON korean 266",
      "lines": [[80463, 81008]],
      "common_name": {"english": "Officer for Jewel", "native": "YeolSaa"}
    },
    {
      "id": "CON korean 267",
      "lines": [[61174, 61174]],
      "common_name": {"english": "Royal", "native": "JwaHaal"}
    },
    {
      "id": "CON korean 268",
      "lines": [[59199, 59199]],
      "common_name": {"english": "Lord", "native": "UuHaal"}
    },
    {
      "id": "CON korean 269",
      "lines": [[60129, 60129]],
      "common_name": {"english": "Left Executor", "native": "JwaJipBeop"}
    },
    {
      "id": "CON korean 270",
      "lines": [[57757, 57757]],
      "common_name": {"english": "Right Executor", "native": "UuJipBeop"}
    },
    {
      "id": "CON korean 271",
      "lines": [[110532, 110273, 110009, 109472]],
      "common_name": {"english": "Crossbeam for Heo", "native": "HeoRyang"}
    },
    {
      "id": "CON korean 272",
      "lines": [[109786, 110391, 110746, 110529, 109990, 109737, 109375, 109786]],
      "common_name": {"english": "Threading Coins", "native": "CheonJeon"}
    }
  ],
  "common_names": {
    "HIP 746": [{"english": "WangRang"}],
    "HIP 2920": [{"english": "CheonSa"}],
    "HIP 3179": [{"english": "CheonSa"}],
    "HIP 3821": [{"english": "CheonSa"}],
    "HIP 4427": [{"english": "CheonSa"}],
    "HIP 5447": [{"english": "DaeJang"}],
    "HIP 9640": [{"english": "DaeJang"}],
    "HIP 21421": [{"english": "CheonGou"}],
    "HIP 23015": [{"english": "Gyeong"}],
    "HIP 24436": [{"english": "PyeonJangGun"}],
    "HIP 24608": [{"english": "CheonGou"}],
    "HIP 25336": [{"english": "UJangGun"}],
    "HIP 25428": [{"english": "CheonChang"}],
    "HIP 25930": [{"english": "SamJangGun"}],
    "HIP 27366": [{"english": "HuJangGun"}],
    "HIP 27989": [{"english": "JwaJangGun"}],
    "HIP 28360": [{"english": "SaGong"}],
    "HIP 28380": [{"english": "CheonOk"}],
    "HIP 33018": [{"english": "JaeSa"}],
    "HIP 34693": [{"english": "JaeUu"}],
    "HIP 36046": [{"english": "SamGong"}],
    "HIP 36962": [{"english": "BakSa"}],
    "HIP 37740": [{"english": "TaeSa"}],
    "HIP 41704": [{"english": "SangJang"}],
    "HIP 44127": [{"english": "SangTae"}],
    "HIP 45075": [{"english": "ChaJang"}],
    "HIP 46733": [{"english": "TaeSang"}],
    "HIP 46853": [{"english": "SaJu.DaeRi"}],
    "HIP 47508": [{"english": "TaeMin"}],
    "HIP 49583": [{"english": "Buin"}],
    "HIP 49637": [{"english": "YeoEo"}],
    "HIP 49669": [{"english": "YeoJu"}],
    "HIP 50335": [{"english": "HuGung"}],
    "HIP 50372": [{"english": "JungTae"}],
    "HIP 50583": [{"english": "WangBi"}],
    "HIP 51233": [{"english": "DaeBu"}],
    "HIP 51624": [{"english": "SouMin"}],
    "HIP 52098": [{"english": "BakSa"}],
    "HIP 53417": [{"english": "EuiSa"}],
    "HIP 53910": [{"english": "Beop"}],
    "HIP 53954": [{"english": "CheoSa"}],
    "HIP 54061": [{"english": "Jeong"}],
    "HIP 55219": [{"english": "HaTae"}],
    "HIP 57632": [{"english": "HwangJae"}],
    "HIP 58001": [{"english": "Ryeong"}],
    "HIP 59774": [{"english": "Beol"}],
    "HIP 60112": [{"english": "HuGung"}],
    "HIP 62572": [{"english": "CheonChu"}],
    "HIP 62956": [{"english": "Sal"}],
    "HIP 65378": [{"english": "Wi"}],
    "HIP 67301": [{"english": "Eung"}],
    "HIP 70692": [{"english": "SeoJa"}],
    "HIP 72607": [{"english": "JaeWang"}],
    "HIP 75097": [{"english": "TaeJa"}],
    "HIP 78104": [{"english": "ChaSang"}],
    "HIP 78265": [{"english": "ChaJang"}],
    "HIP 78401": [{"english": "ChaSang"}],
    "HIP 78820": [{"english": "SangSang"}],
    "HIP 80112": [{"english": "TaeJa"}],
    "HIP 80763": [{"english": "MyeongDang"}],
    "HIP 81266": [{"english": "SeoJa"}],
    "HIP 82396": [{"english": "Hu"}],
    "HIP 82514": [{"english": "Buin"}],
    "HIP 82729": [{"english": "Buin"}],
    "HIP 84143": [{"english": "Buin"}],
    "HIP 86228": [{"english": "Bin"}],
    "HIP 97278": [{"english": "UJangGun"}],
    "HIP 97649": [{"english": "DaeJangGun"}],
    "HIP 98036": [{"english": "JwaJangGun"}]
  }
}
