{
	"version": 13,
	"hipSpectralFile": "stars_hip_sp_0v0_5.cat",
	"objecttypesFile": "object_types_v0_1.cat",
	"catalogs":
	[
		{
			"id": "stars0",
			"fileName": "stars_0_0v0_9.cat",
			"count": 0.005,
			"magRange": [-2, 6],
			"sizeMb": 0.2,
			"checksum": "09458750612460456de0dc142837b4cb",
			"checked": true
		},
		{
			"id": "stars1",
			"fileName": "stars_1_0v0_9.cat",
			"count": 0.022,
			"magRange": [6, 7.5],
			"sizeMb": 1.0,
			"checksum": "cbe557342cf05a7ccf2ff00d80eed494",
			"checked": true
		},
		{
			"id": "stars2",
			"fileName": "stars_2_0v0_9.cat",
			"count": 0.14,
			"magRange": [7.5, 9],
			"sizeMb": 6.5,
			"checksum": "90dc12333f7ba3e83503304b67e29059",
			"checked": true
		},
		{
			"id": "stars3",
			"fileName": "stars_3_1v0_5.cat",
			"count": 0.42,
			"magRange": [9, 10.5],
			"sizeMb": 12.8,
			"checksum": "42b4637c07df823bcd7e1cc5d2ce8f18",
			"checked": true
		},
		{
			"id": "stars4",
			"fileName": "stars_4_1v0_3.cat",
			"count": 1.7,
			"magRange": [10.5, 12],
			"sizeMb": 53.1,
			"url": "https://github.com/Stellarium/stellarium-data/releases/download/stars-3.0/stars_4_1v0_3.cat",
			"checksum": "c0ca96c46f09e5a22752bae07066258b",
			"checked": false
		},
		{
			"id": "stars5",
			"fileName": "stars_5_1v0_2.cat",
			"count": 6.1,
			"magRange": [12, 13.5],
			"sizeMb": 187,
			"url": "https://github.com/Stellarium/stellarium-data/releases/download/stars-3.0/stars_5_1v0_2.cat",
			"checksum": "a9faa40e3f163d9bccf881997a4d565c",
			"checked": false
		},
		{
			"id": "stars6",
			"fileName": "stars_6_1v0_2.cat",
			"count": 19.1,
			"magRange": [13.5, 15],
			"sizeMb": 584,
			"url": "https://github.com/Stellarium/stellarium-data/releases/download/stars-3.0/stars_6_1v0_2.cat",
			"checksum": "e94d4d1d038a09d2df97b955af2d4467",
			"checked": false
		},
		{
			"id": "stars7",
			"fileName": "stars_7_1v0_2.cat",
			"count": 54.5,
			"magRange": [15, 16.5],
			"sizeMb": 1665,
			"url": "https://github.com/Stellarium/stellarium-data/releases/download/stars-3.0/stars_7_1v0_2.cat",
			"checksum": "75dcf325f263e1fdfbc5bb4404f93ba5",
			"checked": false
		},
		{
			"id": "stars8",
			"fileName": "stars_8_2v0_2.cat",
			"count": 138.4,
			"magRange": [16.5, 18],
			"sizeMb": 0,
			"url": "https://dss.stellarium.org/stars-3.0/stars_8_2v0_2.cat",
			"checksum": "d26e528bf8be3131fdf0a63c5180e324",
			"checked": false
		}
	]
}
